Metadata-Version: 2.1
Name: chinese-english-lookup
Version: 0.0.3
Summary: Allows look-up of Chinese words, returning English definitions; parses CC-CEDICT; provides HSK3.0 and HSK2.0 utilities.
Home-page: https://github.com/zenje/chinese-english-lookup
Author: zenje
Author-email: jessicaczeng@gmail.com
License: UNKNOWN
Platform: UNKNOWN
Classifier: Programming Language :: Python :: 3
Classifier: License :: OSI Approved :: MIT License
Classifier: Operating System :: OS Independent
Requires-Python: >=3.6
